ONVIFCameraControl/ONVIFCameraControl.py
ONVIFCameraControl/__init__.py
ONVIFCameraControl/example.py
ONVIFCameraControl-1.0.6.dist-info/LICENSE
ONVIFCameraControl-1.0.6.dist-info/METADATA
ONVIFCameraControl-1.0.6.dist-info/WHEEL
ONVIFCameraControl-1.0.6.dist-info/top_level.txt
ONVIFCameraControl-1.0.6.dist-info/RECORD
