Metadata-Version: 2.1
Name: ONVIFCameraControl
Version: 1.0.6
Summary: Simple camera controls.
Home-page: https://github.com/MikhaelMIEM/ONVIFCameraControl
Author: Mikhael
Author-email: mikhail-miem@yandex.ru
License: UNKNOWN
Platform: UNKNOWN
Classifier: Programming Language :: Python :: 3
Classifier: License :: OSI Approved :: MIT License
Classifier: Operating System :: OS Independent
Requires-Python: >=3.6
Requires-Dist: onvif-zeep (==0.2.12)
Requires-Dist: zeep (==3.4.0)
